marchantia_cv/__init__.py
marchantia_cv/config.py
marchantia_cv/detect_pots.py
marchantia_cv/format_img.py
marchantia_cv/main.py
marchantia_cv/measure_size_watershed.py
marchantia_cv/rotate_img.py
marchantia_cv/split_pots.py
marchantia_cv/warp_img.py
marchantia_cv-0.0.2.dist-info/licenses/LICENSE
marchantia_cv-0.0.2.dist-info/METADATA
marchantia_cv-0.0.2.dist-info/WHEEL
marchantia_cv-0.0.2.dist-info/top_level.txt
marchantia_cv-0.0.2.dist-info/RECORD
