Metadata-Version: 2.4
Name: marchantia_cv
Version: 0.0.2
Summary: Automated phenotyping of Marchantia polymorpha
Author-email: Philippa Hill <pippi.r.hill@gmail.com>
License-Expression: MIT
Project-URL: Homepage, https://github.com/HighlanderLab/phill_gxe_pheno
Project-URL: Issues, https://github.com/HighlanderLab/phill_gxe_pheno/issues
Classifier: Programming Language :: Python :: 3
Classifier: Operating System :: OS Independent
Requires-Python: >=3.9
License-File: LICENSE
Dynamic: license-file
